fluxa/__init__.py
fluxa/__init__.pyi
fluxa/_internal.py
fluxa/_lowlevel.abi3.so
fluxa/_lowlevel.pyi
fluxa/async_support.py
fluxa/debug.py
fluxa/i18n.py
fluxa/py.typed
fluxa/sandbox.py
fluxa-0.1.1.dist-info/METADATA
fluxa-0.1.1.dist-info/WHEEL
fluxa-0.1.1.dist-info/licenses/LICENSE
fluxa-0.1.1.dist-info/RECORD
